httomo/__init__.py
httomo/__main__.py
httomo/base_block.py
httomo/block_interfaces.py
httomo/cli.py
httomo/cli_utils.py
httomo/darks_flats.py
httomo/globals.py
httomo/logger.py
httomo/methods.py
httomo/preview.py
httomo/transform_layer.py
httomo/transform_loader_params.py
httomo/types.py
httomo/ui_layer.py
httomo/utils.py
httomo/yaml_checker.py
httomo/data/__init__.py
httomo/data/dataset_store.py
httomo/data/mpiutil.py
httomo/data/padding.py
httomo/data/param_sweep_store.py
httomo/data/hdf/__init__.py
httomo/data/hdf/_utils/__init__.py
httomo/data/hdf/_utils/chunk.py
httomo/data/hdf/_utils/reslice.py
httomo/loaders/__init__.py
httomo/loaders/standard_tomo_loader.py
httomo/loaders/types.py
httomo/method_wrappers/__init__.py
httomo/method_wrappers/datareducer.py
httomo/method_wrappers/dezinging.py
httomo/method_wrappers/distortion_correction.py
httomo/method_wrappers/generic.py
httomo/method_wrappers/images.py
httomo/method_wrappers/reconstruction.py
httomo/method_wrappers/rotation.py
httomo/method_wrappers/save_intermediate.py
httomo/method_wrappers/stats_calc.py
httomo/monitors/__init__.py
httomo/monitors/aggregate.py
httomo/monitors/benchmark.py
httomo/monitors/summary.py
httomo/runner/__init__.py
httomo/runner/auxiliary_data.py
httomo/runner/block_split.py
httomo/runner/dataset.py
httomo/runner/dataset_store_backing.py
httomo/runner/dataset_store_interfaces.py
httomo/runner/gpu_utils.py
httomo/runner/loader.py
httomo/runner/method_wrapper.py
httomo/runner/methods_repository_interface.py
httomo/runner/monitoring_interface.py
httomo/runner/output_ref.py
httomo/runner/pipeline.py
httomo/runner/section.py
httomo/runner/task_runner.py
httomo/sweep_runner/__init__.py
httomo/sweep_runner/param_sweep_block.py
httomo/sweep_runner/param_sweep_json_loader.py
httomo/sweep_runner/param_sweep_runner.py
httomo/sweep_runner/param_sweep_store_interfaces.py
httomo/sweep_runner/param_sweep_yaml_loader.py
httomo/sweep_runner/side_output_manager.py
httomo/sweep_runner/stages.py
httomo-3.0.dist-info/licenses/LICENSE
httomo-3.0.dist-info/METADATA
httomo-3.0.dist-info/WHEEL
httomo-3.0.dist-info/entry_points.txt
httomo-3.0.dist-info/top_level.txt
httomo-3.0.dist-info/RECORD
