Metadata-Version: 2.4
Name: httomo
Version: 3.0
Summary: High Throughput Tomography framework.
Author: Garry ODonnell, Jacob Williamson
Author-email: Daniil Kazantsev <daniil.kazantsev@diamond.ac.uk>, Yousef Moazzam <yousef.moazzam@diamond.ac.uk>, Jessica Verschoyle <jessica.verschoyle@diamond.ac.uk>, Naman Gera <naman.gera@diamond.ac.uk>, scientificsoftware@diamond.ac.uk
License: BSD-3-Clause
Project-URL: repository, https://github.com/DiamondLightSource/HTTomo
Classifier: Development Status :: 4 - Beta
Classifier: License :: OSI Approved :: BSD License
Classifier: Programming Language :: Python :: 3.10
Requires-Python: >=3.10
License-File: LICENSE
Requires-Dist: click
Requires-Dist: cupy
Requires-Dist: numpy
Requires-Dist: hdf5plugin
Requires-Dist: httomo-backends
Requires-Dist: loguru
Requires-Dist: mpi4py
Requires-Dist: pyyaml
Requires-Dist: tqdm
Requires-Dist: graypy
Provides-Extra: cpu
Requires-Dist: httomolib; extra == "cpu"
Provides-Extra: gpu
Requires-Dist: httomolibgpu; extra == "gpu"
Provides-Extra: dev-cpu
Requires-Dist: pytest; extra == "dev-cpu"
Requires-Dist: pytest-cov; extra == "dev-cpu"
Requires-Dist: pytest-xdist; extra == "dev-cpu"
Requires-Dist: pytest-mock; extra == "dev-cpu"
Requires-Dist: flake8; extra == "dev-cpu"
Requires-Dist: pyproject-flake8; extra == "dev-cpu"
Requires-Dist: pydocstyle; extra == "dev-cpu"
Requires-Dist: httomolib[dev]; extra == "dev-cpu"
Requires-Dist: plumbum; extra == "dev-cpu"
Requires-Dist: mypy; extra == "dev-cpu"
Requires-Dist: types-PyYAML; extra == "dev-cpu"
Requires-Dist: pre-commit; extra == "dev-cpu"
Provides-Extra: dev-gpu
Requires-Dist: pytest; extra == "dev-gpu"
Requires-Dist: pytest-cov; extra == "dev-gpu"
Requires-Dist: pytest-xdist; extra == "dev-gpu"
Requires-Dist: pytest-mock; extra == "dev-gpu"
Requires-Dist: flake8; extra == "dev-gpu"
Requires-Dist: pyproject-flake8; extra == "dev-gpu"
Requires-Dist: pydocstyle; extra == "dev-gpu"
Requires-Dist: httomolib[dev]; extra == "dev-gpu"
Requires-Dist: httomolibgpu[dev]; extra == "dev-gpu"
Requires-Dist: plumbum; extra == "dev-gpu"
Requires-Dist: mypy; extra == "dev-gpu"
Requires-Dist: types-PyYAML; extra == "dev-gpu"
Requires-Dist: pre-commit; extra == "dev-gpu"
Requires-Dist: ccpi-regularisation-cupy; extra == "dev-gpu"
Dynamic: license-file
